README.md
setup.py
pysnapshot/__init__.py
pysnapshot/snap.py
pysnapshot.egg-info/PKG-INFO
pysnapshot.egg-info/SOURCES.txt
pysnapshot.egg-info/dependency_links.txt
pysnapshot.egg-info/top_level.txt