Metadata-Version: 2.1
Name: pysnapshot
Version: 0.1.0a0
Summary: Take snapshots of your codebase and reload them easily later.
Home-page: https://github.com/pseeth/pysnapshot
Author: Prem Seetharaman
Author-email: prem@descript.com
License: MIT
Keywords: machine learning,experimentation
Platform: UNKNOWN
Classifier: Intended Audience :: Developers
Classifier: Intended Audience :: Education
Classifier: Intended Audience :: Science/Research
Classifier: Natural Language :: English
Classifier: Programming Language :: Python :: 3.7
Classifier: Topic :: Artistic Software
Classifier: Topic :: Multimedia
Classifier: Topic :: Multimedia :: Sound/Audio
Classifier: Topic :: Multimedia :: Sound/Audio :: Editors
Classifier: Topic :: Software Development :: Libraries
